take_text_preprocess/__init__.py
take_text_preprocess/data/__init__.py
take_text_preprocess/data/validate_inputs.py
take_text_preprocess/logic/__init__.py
take_text_preprocess/logic/abbreviations.py
take_text_preprocess/logic/add_space_to_puct.py
take_text_preprocess/logic/lower_case.py
take_text_preprocess/logic/remove_non_ascii_symbols.py
take_text_preprocess/logic/replace_abbreviations.py
take_text_preprocess/logic/basic_preprocessing/__init__.py
take_text_preprocess/logic/basic_preprocessing/abbreviations.py
take_text_preprocess/logic/basic_preprocessing/basic_callable.py
take_text_preprocess/logic/basic_preprocessing/lower_case.py
take_text_preprocess/logic/basic_preprocessing/remove_non_ascii.py
take_text_preprocess/logic/basic_preprocessing/replace_abbreviations.py
take_text_preprocess/logic/decision_pipeline/__init__.py
take_text_preprocess/logic/decision_pipeline/pipeline.py
take_text_preprocess/logic/regex_preprocessing/__init__.py
take_text_preprocess/logic/regex_preprocessing/regex_callable.py
take_text_preprocess/logic/regex_preprocessing/replace_regex.py
take_text_preprocess/logic/scanner_tokenization/__init__.py
take_text_preprocess/logic/scanner_tokenization/scanner.py
take_text_preprocess/logic/scanner_tokenization/scanner_get_tokens.py
take_text_preprocess/logic/scanner_tokenization/tokenize_text.py
take_text_preprocess/presentation/__init__.py
take_text_preprocess/presentation/presentation.py
text_preprocess/__init__.py
text_preprocess/data/__init__.py
text_preprocess/data/validate_inputs.py
text_preprocess/logic/__init__.py
text_preprocess/logic/add_space_to_puct.py
text_preprocess/logic/lower_case.py
text_preprocess/logic/remove_non_ascii.py
text_preprocess/logic/replace_regex.py
text_preprocess/logic/basic_preprocessing/__init__.py
text_preprocess/logic/basic_preprocessing/basic_callable.py
text_preprocess/logic/basic_preprocessing/lower_case.py
text_preprocess/logic/basic_preprocessing/remove_non_ascii.py
take_text_preprocess-0.0.5.dist-info/METADATA
take_text_preprocess-0.0.5.dist-info/WHEEL
take_text_preprocess-0.0.5.dist-info/top_level.txt
take_text_preprocess-0.0.5.dist-info/RECORD
