Metadata-Version: 2.1
Name: take-text-preprocess
Version: 0.0.5
Summary: Text Preprocesser
Home-page: UNKNOWN
Author: Data & Analytics Research
Author-email: analytics.dar@take.net
Maintainer: daresearch
Maintainer-email: anaytics.dar@take.net
License: MIT License
Keywords: text,preprocessing
Platform: UNKNOWN
Classifier: Programming Language :: Python :: 3
Classifier: Operating System :: OS Independent
Requires-Dist: Unidecode (==1.1.1)
Requires-Dist: pytest (~=5.3.5)
Requires-Dist: setuptools (~=45.2.0)
